<scene id="0MF|Sy6!LLy9|Em|LiftedLotusKm+01Kx" actors="2" style="OScene">
<info name="Lifted Lotus, Unkiss |+ UnKiss" animator="Ceo"/>
<anim id="0Sx0MF_Em-LiftedLotusKm+01Kx" t="T" l="2.0" dest="0MF|Sy6!LLy9|Em|LiftedLotusEmb">
<mfx a= "0">
<fx0 ti=".5" cmd="EVNT">
	<evnt cmd="actor" type="kiss" subtype="KissExit" drive="intimate">
	<eyes><look v="-95" h="-90" vpan="5" hpan="10"/></eyes>
	</evnt>
</fx0>
<fx1 ti=".5" cmd="EVNT">
	<evnt cmd="actor" type="kiss" subtype="KissExit" drive="intimate">
	<eyes><look v="-95" h="-90" vpan="5" hpan="10"/></eyes>
	</evnt>
</fx1>
</mfx>
<mfx a= "1">
<fx0 ti=".5" cmd="EVNT">
	<evnt cmd="actor" type="kiss" subtype="KissExit" drive="intimate">
	<eyes><look v="-95" h="-90" vpan="5" hpan="10"/></eyes>
	</evnt>
</fx0>
<fx1 ti=".5" cmd="EVNT">
	<evnt cmd="actor" type="kiss" subtype="KissExit" drive="intimate">
	<eyes><look v="-95" h="-90" vpan="5" hpan="10"/></eyes>
	</evnt>
</fx1>
</mfx>
</anim>
</scene>
